{
  "timeZone": "America/Los_Angeles",
  "exceptionLogging": "STACKDRIVER",
  "runtimeVersion": "V8",
  "dependencies": {
    "libraries": [
      {
        "userSymbol": "RWGPSLib",
        "libraryId": "1LrtdhxRlvd3Ep5Z2M7KCrii6VlMiFLR8Q39X24y7qV-0DsBDl-76qivO",
        "version": "7",
        "developmentMode": false
      },
      {
        "userSymbol": "dates",
        "version": "2",
        "libraryId": "1xKrJ6uL--imEHP9SkAyUIMhcrpI6cfPACJ_4Hb_XpsDbQof19W1y7qRE",
        "developmentMode": false
      },
      {
        "userSymbol": "bmPreFiddler",
        "version": "34",
        "libraryId": "13JUFGY18RHfjjuKmIRRfvmGlCYrEkEtN6uUm-iLUcxOUFRJD-WBX-tkR"
      }
    ]
  },
  "sheets": {
    "macros": [
      {
        "menuName": "SatA",
        "functionName": "SatA"
      },
      {
        "menuName": "Unlink Route",
        "functionName": "UnlinkRoute"
      }
    ]
  },
  "oauthScopes": [
    "https://www.googleapis.com/auth/calendar",
    "https://www.googleapis.com/auth/script.external_request",
    "https://www.googleapis.com/auth/spreadsheets.currentonly"
  ]
}